{
	"title": "Expandir",
	"text": "Adecuado para necesidades a largo plazo y tareas continuas",
	"time": "30+ houras",
	"info": {
		"couching": [
			"Haciendo seguimiento con inversores, productores, patrocinadores",
			"Pulir tu inglés empresarial"
		],
		"translation": [
			"Websites nuevos o actualizados",
			"Nuevos o actualizados",
			{
				"id": "Material de comunicación",
				"data": [
					"Boletines periódicos",
					"Contenido regular en redes sociales",
					"etc."
				]
			}
		]
	}
}
